odoo/addons/easy_my_coop_loan_website/README.rst
odoo/addons/easy_my_coop_loan_website/__init__.py
odoo/addons/easy_my_coop_loan_website/__manifest__.py
odoo/addons/easy_my_coop_loan_website/controllers/__init__.py
odoo/addons/easy_my_coop_loan_website/controllers/main.py
odoo/addons/easy_my_coop_loan_website/data/website_loan_data.xml
odoo/addons/easy_my_coop_loan_website/i18n/easy_my_coop_loan_website.pot
odoo/addons/easy_my_coop_loan_website/readme/CONTRIBUTORS.rst
odoo/addons/easy_my_coop_loan_website/readme/DESCRIPTION.rst
odoo/addons/easy_my_coop_loan_website/static/description/index.html
odoo/addons/easy_my_coop_loan_website/static/src/js/loan_issue.js
odoo/addons/easy_my_coop_loan_website/template/loan_issue_template.xml
odoo12_addon_easy_my_coop_loan_website-12.0.1.0.1.99.dev15.dist-info/METADATA
odoo12_addon_easy_my_coop_loan_website-12.0.1.0.1.99.dev15.dist-info/WHEEL
odoo12_addon_easy_my_coop_loan_website-12.0.1.0.1.99.dev15.dist-info/top_level.txt
odoo12_addon_easy_my_coop_loan_website-12.0.1.0.1.99.dev15.dist-info/RECORD
