Metadata-Version: 2.1
Name: odoo12-addon-easy-my-coop-loan-website
Version: 12.0.1.0.1.99.dev15
Summary: This module implements the subscription page for bonds and subordinated loans.
Home-page: https://coopiteasy.be
Author: Coop IT Easy SCRLfs
License: AGPL-3
Platform: UNKNOWN
Classifier: Programming Language :: Python
Classifier: Framework :: Odoo
Classifier: Framework :: Odoo :: 12.0
Classifier: License :: OSI Approved :: GNU Affero General Public License v3
Requires-Python: >=3.5
Requires-Dist: odoo12-addon-auth-company-signup
Requires-Dist: odoo12-addon-easy-my-coop-loan
Requires-Dist: odoo12-addon-easy-my-coop-website-portal
Requires-Dist: odoo (<12.1dev,>=12.0a)
